{
    "variables": {
        "password": "Administr@tor",
        "disk_size": "61440"
    },
    
    "builders": [
        {
            "type": "qemu",
            "name": "windows-2012R2",
            "format":"qcow2",
            "accelerator": "kvm",
            "disk_size": "{{ user `disk_size`}}",

            "iso_url": "http://care.dlservice.microsoft.com/dl/download/6/2/A/62A76ABB-9990-4EFC-A4FE-C7D698DAEB96/9600.17050.WINBLUE_REFRESH.140317-1640_X64FRE_SERVER_EVAL_EN-US-IR3_SSS_X64FREE_EN-US_DV9.ISO",
            "iso_checksum_type": "md5",
            "iso_checksum": "5b5e08c490ad16b59b1d9fab0def883a",

            "boot_wait": "2m",
            "ssh_username": "Administrator",
            "ssh_password": "Administrator",
            "shutdown_command": "shutdown /s /t 10 /f /d p:4:1 /c \"Packer Shutdown\"",

            "floppy_files": [
                "floppy/drivers/virtio-win-0.1-81/WIN7/AMD64/*",
                "floppy/common/*",
                "floppy/windows-2012-standard-amd64/*"
            ],
            "disk_interface":"virtio",
            "qemuargs": [
                ["-m", "4096m"],
                ["-smp", 2]
            ]
        }
    ],

    "provisioners": [
        {
            "type": "shell",
            "inline": ["net user Administrator {{ user `password`}}"]
        },

        {
            "type": "shell",
            "remote_path": "/cygdrive/c/Windows/Temp/script.bat",
            "execute_command": "cmd /c C:/Windows/Temp/script.bat",
            "scripts": [
                "scripts/enable-rdp.bat",
                "scripts/execution-policy-unrestricted.bat",
                "scripts/unlimited-password-expiration.bat"
            ]
        }
    ]
}
